tempuscator/__init__.py
tempuscator/archiver.py
tempuscator/arguments.py
tempuscator/base.py
tempuscator/cli.py
tempuscator/constants.py
tempuscator/engines.py
tempuscator/exceptions.py
tempuscator/executor.py
tempuscator/helpers.py
tempuscator/logger.py
tempuscator/repo.py
tempuscator/sentry.py
tempuscator/swapper.py
tempuscator-0.3.0a6.dist-info/LICENSE
tempuscator-0.3.0a6.dist-info/METADATA
tempuscator-0.3.0a6.dist-info/WHEEL
tempuscator-0.3.0a6.dist-info/entry_points.txt
tempuscator-0.3.0a6.dist-info/RECORD
