Metadata-Version: 2.1
Name: tempuscator
Version: 0.3.0a6
Summary: Script to run some sqls
Home-page: https://github.com/niekosau
License: GPL-3.0-only
Author: Arunas Grigalionis
Author-email: arunas.grigalionis@gmail.com
Requires-Python: >=3.9,<3.10
Classifier: License :: OSI Approved :: GNU General Public License v3 (GPLv3)
Classifier: Programming Language :: Python :: 3
Classifier: Programming Language :: Python :: 3.9
Requires-Dist: gitpython (>=3.1.43,<4.0.0)
Requires-Dist: inotify (>=0.2.10,<0.3.0)
Requires-Dist: psutil (>=6.0.0,<7.0.0)
Requires-Dist: pymysql (>=1.1.1,<2.0.0)
Requires-Dist: sentry-sdk (>=2.13.0,<3.0.0)
Requires-Dist: sqlalchemy (>=2.0.32,<3.0.0)
Project-URL: Repository, https://github.com/niekosau/tempuscator
